[{"": "25600", "id": "31145376", "name": "Rental unit in Los Angeles \u00b7 \u26054.77 \u00b7 2 bedrooms \u00b7 2 beds \u00b7 2 baths", "host_id": "7356043", "price": "$280.00", "minimum_nights": "30", "maximum_nights": "90", "availability_365": "89"}, {"": "25601", "id": "799421549094228137", "name": "Home in Los Angeles \u00b7 3 bedrooms \u00b7 4 beds \u00b7 2.5 baths", "host_id": "276044294", "price": "$700.00", "minimum_nights": "2", "maximum_nights": "365", "availability_365": "364"}, {"": "25602", "id": "23544801", "name": "Rental unit in Los Angeles \u00b7 \u26054.73 \u00b7 2 bedrooms \u00b7 3 beds \u00b7 2 baths", "host_id": "175525180", "price": "$379.00", "minimum_nights": "30", "maximum_nights": "30", "availability_365": "90"}, {"": "25603", "id": "855653022018834183", "name": "Rental unit in Los Angeles \u00b7 2 bedrooms \u00b7 2 beds \u00b7 2 baths", "host_id": "151677268", "price": "$600.00", "minimum_nights": "31", "maximum_nights": "365", "availability_365": "365"}, {"": "25604", "id": "968247089019035182", "name": "Rental unit in Los Angeles \u00b7 \u2605New \u00b7 Studio \u00b7 1 bed \u00b7 1 bath", "host_id": "30850484", "price": "$180.00", "minimum_nights": "30", "maximum_nights": "365", "availability_365": "311"}, {"": "25605", "id": "30320899", "name": "Home in Los Angeles \u00b7 \u26054.63 \u00b7 1 bedroom \u00b7 1 bed \u00b7 1 bath", "host_id": "9037281", "price": "$130.00", "minimum_nights": "30", "maximum_nights": "30", "availability_365": "62"}, {"": "25606", "id": "821962893819996609", "name": "Home in Los Angeles \u00b7 \u26054.14 \u00b7 5 bedrooms \u00b7 6 beds \u00b7 5.5 baths", "host_id": "96071540", "price": "$1,157.00", "minimum_nights": "30", "maximum_nights": "365", "availability_365": "109"}, {"": "25607", "id": "806943579713452903", "name": "Rental unit in Los Angeles \u00b7 \u26054.73 \u00b7 2 bedrooms \u00b7 3 beds \u00b7 2 baths", "host_id": "230016718", "price": "$268.00", "minimum_nights": "2", "maximum_nights": "30", "availability_365": "145"}, {"": "25608", "id": "906867349473658950", "name": "Home in Vernon \u00b7 1 bedroom \u00b7 1 bed \u00b7 1 bath", "host_id": "390414536", "price": "$80.00", "minimum_nights": "1", "maximum_nights": "365", "availability_365": "365"}, {"": "25609", "id": "32865975", "name": "Guest suite in Santa Monica \u00b7 \u26054.88 \u00b7 Studio \u00b7 1 bed \u00b7 1 bath", "host_id": "29820038", "price": "$210.00", "minimum_nights": "2", "maximum_nights": "30", "availability_365": "130"}, {"": "25610", "id": "50851392", "name": "Serviced apartment in Los Angeles County \u00b7 1 bedroom \u00b7 1 bath", "host_id": "411105192", "price": "$115.00", "minimum_nights": "30", "maximum_nights": "365", "availability_365": "365"}, {"": "25611", "id": "18273632", "name": "Hostel in Los Angeles \u00b7 \u26054.46 \u00b7 1 bedroom \u00b7 1 bed \u00b7 4 shared baths", "host_id": "26860", "price": "$60.00", "minimum_nights": "30", "maximum_nights": "365", "availability_365": "210"}, {"": "25612", "id": "50248436", "name": "Loft in Los Angeles \u00b7 \u26055.0 \u00b7 1 bedroom \u00b7 3 beds \u00b7 1 bath", "host_id": "4638643", "price": "$150.00", "minimum_nights": "30", "maximum_nights": "120", "availability_365": "40"}, {"": "25613", "id": "29456236", "name": "Rental unit in Santa Monica \u00b7 \u26054.91 \u00b7 1 bedroom \u00b7 1 bed \u00b7 1 bath", "host_id": "137877395", "price": "$136.00", "minimum_nights": "31", "maximum_nights": "1125", "availability_365": "264"}, {"": "25614", "id": "828987776863513876", "name": "Rental unit in Los Angeles \u00b7 Studio \u00b7 1 bed \u00b7 1 bath", "host_id": "489981075", "price": "$84.00", "minimum_nights": "31", "maximum_nights": "365", "availability_365": "354"}, {"": "25615", "id": "38910839", "name": "Rental unit in West Covina \u00b7 3 bedrooms \u00b7 3 beds \u00b7 2.5 baths", "host_id": "28575618", "price": "$259.00", "minimum_nights": "28", "maximum_nights": "180", "availability_365": "361"}, {"": "25616", "id": "620816291542624006", "name": "Rental unit in Santa Monica \u00b7 \u26054.94 \u00b7 1 bedroom \u00b7 1 bed \u00b7 1 bath", "host_id": "375121309", "price": "$248.00", "minimum_nights": "1", "maximum_nights": "365", "availability_365": "276"}, {"": "25617", "id": "22017525", "name": "Rental unit in Los Angeles \u00b7 \u26054.36 \u00b7 2 bedrooms \u00b7 3 beds \u00b7 1 bath", "host_id": "30572195", "price": "$145.00", "minimum_nights": "30", "maximum_nights": "1125", "availability_365": "0"}, {"": "25618", "id": "48568802", "name": "Rental unit in Santa Monica \u00b7 \u26055.0 \u00b7 1 bedroom \u00b7 1 bed \u00b7 1 bath", "host_id": "137877395", "price": "$138.00", "minimum_nights": "31", "maximum_nights": "365", "availability_365": "269"}, {"": "25619", "id": "877646514381622770", "name": "Townhouse in Los Angeles \u00b7 3 bedrooms \u00b7 6 beds \u00b7 3 baths", "host_id": "14727082", "price": "$129.00", "minimum_nights": "30", "maximum_nights": "365", "availability_365": "274"}, {"": "25620", "id": "46336338", "name": "Villa in Los Angeles \u00b7 5 bedrooms \u00b7 5 beds \u00b7 6.5 baths", "host_id": "328127972", "price": "$2,000.00", "minimum_nights": "31", "maximum_nights": "1125", "availability_365": "0"}, {"": "25621", "id": "644244248062773253", "name": "Rental unit in Los Angeles \u00b7 Studio \u00b7 1 bed \u00b7 1 bath", "host_id": "374464274", "price": "$90.00", "minimum_nights": "31", "maximum_nights": "365", "availability_365": "288"}, {"": "25622", "id": "697756514585251317", "name": "Rental unit in Santa Monica \u00b7 \u26054.62 \u00b7 1 bedroom \u00b7 1 bed \u00b7 1 bath", "host_id": "392789878", "price": "$195.00", "minimum_nights": "1", "maximum_nights": "29", "availability_365": "90"}, {"": "25623", "id": "46106823", "name": "Rental unit in Santa Monica \u00b7 \u26054.40 \u00b7 Studio \u00b7 1 bed \u00b7 1 bath", "host_id": "137877395", "price": "$95.00", "minimum_nights": "31", "maximum_nights": "1125", "availability_365": "365"}, {"": "25624", "id": "620849396281055522", "name": "Rental unit in Santa Monica \u00b7 \u26054.85 \u00b7 1 bedroom \u00b7 1 bed \u00b7 1 bath", "host_id": "375121309", "price": "$189.00", "minimum_nights": "1", "maximum_nights": "365", "availability_365": "331"}, {"": "25625", "id": "789439831671112312", "name": "Serviced apartment in Los Angeles \u00b7 \u26055.0 \u00b7 1 bedroom \u00b7 1 bed \u00b7 1 bath", "host_id": "418222370", "price": "$223.00", "minimum_nights": "1", "maximum_nights": "365", "availability_365": "82"}, {"": "25626", "id": "940226502083356021", "name": "Rental unit in Santa Monica \u00b7 \u2605New \u00b7 1 bedroom \u00b7 1 bed \u00b7 1 bath", "host_id": "42062430", "price": "$251.00", "minimum_nights": "3", "maximum_nights": "365", "availability_365": "240"}, {"": "25627", "id": "618423198825215156", "name": "Camper/RV in Marina del Rey \u00b7 1 bedroom \u00b7 1 bed \u00b7 Shared half-bath", "host_id": "39528519", "price": "$17.00", "minimum_nights": "30", "maximum_nights": "1125", "availability_365": "365"}, {"": "25628", "id": "4310757", "name": "Guesthouse in Santa Monica \u00b7 \u26054.56 \u00b7 1 bedroom \u00b7 2 beds \u00b7 1 bath", "host_id": "22376246", "price": "$160.00", "minimum_nights": "1", "maximum_nights": "1125", "availability_365": "323"}, {"": "25629", "id": "883371126758506292", "name": "Rental unit in Los Angeles \u00b7 \u26055.0 \u00b7 1 bedroom \u00b7 1 bed \u00b7 1 bath", "host_id": "430094148", "price": "$203.00", "minimum_nights": "5", "maximum_nights": "365", "availability_365": "73"}, {"": "25630", "id": "49800263", "name": "Serviced apartment in Los Angeles \u00b7 Studio \u00b7 2 beds \u00b7 1 bath", "host_id": "103997766", "price": "$215.00", "minimum_nights": "30", "maximum_nights": "1125", "availability_365": "365"}, {"": "25631", "id": "35948700", "name": "Guest suite in Los Angeles \u00b7 \u26054.98 \u00b7 1 bedroom \u00b7 1 bed \u00b7 1 bath", "host_id": "34703692", "price": "$83.00", "minimum_nights": "30", "maximum_nights": "90", "availability_365": "323"}, {"": "25632", "id": "52390670", "name": "Rental unit in Los Angeles \u00b7 1 bedroom \u00b7 2 beds \u00b7 1 bath", "host_id": "17739626", "price": "$160.00", "minimum_nights": "30", "maximum_nights": "1125", "availability_365": "365"}, {"": "25633", "id": "19966938", "name": "Rental unit in Santa Monica \u00b7 \u26054.76 \u00b7 1 bedroom \u00b7 2 beds \u00b7 1 bath", "host_id": "137877395", "price": "$120.00", "minimum_nights": "31", "maximum_nights": "1125", "availability_365": "158"}, {"": "25634", "id": "5784111", "name": "Bungalow in Hermosa Beach \u00b7 \u26054.85 \u00b7 1 bedroom \u00b7 2 beds \u00b7 1 bath", "host_id": "15021342", "price": "$195.00", "minimum_nights": "3", "maximum_nights": "1125", "availability_365": "0"}, {"": "25635", "id": "913392689015112968", "name": "Home in Gardena \u00b7 1 bedroom \u00b7 1 bed \u00b7 1 bath", "host_id": "390414536", "price": "$80.00", "minimum_nights": "1", "maximum_nights": "365", "availability_365": "363"}, {"": "25636", "id": "968485020477615906", "name": "Home in Long Beach \u00b7 \u2605New \u00b7 2 bedrooms \u00b7 2 beds \u00b7 1 bath", "host_id": "57309930", "price": "$173.00", "minimum_nights": "1", "maximum_nights": "25", "availability_365": "80"}, {"": "25637", "id": "1628111", "name": "Rental unit in Los Angeles \u00b7 \u26054.24 \u00b7 Studio \u00b7 1 bed \u00b7 1 bath", "host_id": "7089643", "price": "$54.00", "minimum_nights": "31", "maximum_nights": "1125", "availability_365": "195"}, {"": "25638", "id": "54199759", "name": "Home in Los Angeles \u00b7 \u26054.93 \u00b7 3 bedrooms \u00b7 3 beds \u00b7 2 baths", "host_id": "439449360", "price": "$480.00", "minimum_nights": "4", "maximum_nights": "30", "availability_365": "229"}, {"": "25639", "id": "583360259609224812", "name": "Loft in Los Angeles \u00b7 \u26054.97 \u00b7 1 bedroom \u00b7 1 bed \u00b7 1 bath", "host_id": "2825358", "price": "$185.00", "minimum_nights": "4", "maximum_nights": "10", "availability_365": "53"}, {"": "25640", "id": "773297409700090077", "name": "Rental unit in Los Angeles \u00b7 Studio \u00b7 1 bed \u00b7 1 bath", "host_id": "489981075", "price": "$91.00", "minimum_nights": "31", "maximum_nights": "365", "availability_365": "63"}, {"": "25641", "id": "28657708", "name": "Rental unit in venice \u00b7 \u26054.89 \u00b7 1 bedroom \u00b7 1 bed \u00b7 1 bath", "host_id": "9151182", "price": "$175.00", "minimum_nights": "30", "maximum_nights": "1125", "availability_365": "344"}, {"": "25642", "id": "866103728708672776", "name": "Rental unit in Marina del Rey \u00b7 \u26054.50 \u00b7 1 bedroom \u00b7 1 bed \u00b7 1 bath", "host_id": "210321294", "price": "$242.00", "minimum_nights": "3", "maximum_nights": "365", "availability_365": "180"}, {"": "25643", "id": "887766700132601060", "name": "Home in Los Angeles \u00b7 2 bedrooms \u00b7 2 beds \u00b7 2.5 baths", "host_id": "60123928", "price": "$643.00", "minimum_nights": "2", "maximum_nights": "365", "availability_365": "41"}, {"": "25644", "id": "18174694", "name": "Rental unit in Los Angeles \u00b7 \u26054.65 \u00b7 Studio \u00b7 2 beds \u00b7 1 bath", "host_id": "95305280", "price": "$155.00", "minimum_nights": "30", "maximum_nights": "1125", "availability_365": "347"}, {"": "25645", "id": "950086796734181915", "name": "Rental unit in Santa Monica \u00b7 \u2605New \u00b7 1 bedroom \u00b7 3 beds \u00b7 1 bath", "host_id": "455429593", "price": "$187.00", "minimum_nights": "2", "maximum_nights": "365", "availability_365": "204"}, {"": "25646", "id": "53420590", "name": "Rental unit in Los Angeles \u00b7 Studio \u00b7 1 bath", "host_id": "411105192", "price": "$115.00", "minimum_nights": "30", "maximum_nights": "1125", "availability_365": "364"}, {"": "25647", "id": "858992832713965056", "name": "Home in Los Angeles \u00b7 \u26055.0 \u00b7 2 bedrooms \u00b7 3 beds \u00b7 1.5 baths", "host_id": "20610544", "price": "$500.00", "minimum_nights": "2", "maximum_nights": "365", "availability_365": "314"}, {"": "25648", "id": "23021567", "name": "Rental unit in Los Angeles \u00b7 \u26054.56 \u00b7 Studio \u00b7 1 bed \u00b7 1 bath", "host_id": "159480876", "price": "$115.00", "minimum_nights": "31", "maximum_nights": "1125", "availability_365": "101"}, {"": "25649", "id": "46021255", "name": "Home in Los Angeles \u00b7 6 bedrooms \u00b7 6 beds \u00b7 2 baths", "host_id": "86375582", "price": "$1,000.00", "minimum_nights": "30", "maximum_nights": "1125", "availability_365": "0"}, {"": "25650", "id": "44998571", "name": "Rental unit in Los Angeles \u00b7 \u26055.0 \u00b7 1 bedroom \u00b7 1 bed \u00b7 1 bath", "host_id": "13992754", "price": "$129.00", "minimum_nights": "30", "maximum_nights": "1125", "availability_365": "351"}, {"": "25651", "id": "3993975", "name": "Townhouse in Los Angeles \u00b7 \u26054.29 \u00b7 3 bedrooms \u00b7 7 beds \u00b7 3 baths", "host_id": "14727082", "price": "$104.00", "minimum_nights": "30", "maximum_nights": "730", "availability_365": "331"}, {"": "25652", "id": "45055475", "name": "Rental unit in Manhattan Beach \u00b7 1 bedroom \u00b7 2 beds \u00b7 1 bath", "host_id": "363516460", "price": "$185.00", "minimum_nights": "30", "maximum_nights": "1125", "availability_365": "0"}, {"": "25653", "id": "761042318187139809", "name": "Home in Los Angeles \u00b7 \u26055.0 \u00b7 2 bedrooms \u00b7 3 beds \u00b7 1 bath", "host_id": "7978870", "price": "$346.00", "minimum_nights": "4", "maximum_nights": "27", "availability_365": "108"}, {"": "25654", "id": "8538197", "name": "Townhouse in Los Angeles \u00b7 \u26054.25 \u00b7 3 bedrooms \u00b7 8 beds \u00b7 2 baths", "host_id": "14727082", "price": "$105.00", "minimum_nights": "30", "maximum_nights": "365", "availability_365": "278"}, {"": "25655", "id": "872539236003590570", "name": "Townhouse in Los Angeles \u00b7 3 bedrooms \u00b7 6 beds \u00b7 2 baths", "host_id": "14727082", "price": "$105.00", "minimum_nights": "30", "maximum_nights": "365", "availability_365": "257"}, {"": "25656", "id": "48057289", "name": "Rental unit in Los Angeles \u00b7 \u26054.86 \u00b7 2 bedrooms \u00b7 2 beds \u00b7 2 baths", "host_id": "374464274", "price": "$125.00", "minimum_nights": "31", "maximum_nights": "365", "availability_365": "260"}, {"": "25657", "id": "19551799", "name": "Townhouse in Los Angeles \u00b7 \u26054.48 \u00b7 3 bedrooms \u00b7 7 beds \u00b7 3 baths", "host_id": "14727082", "price": "$109.00", "minimum_nights": "30", "maximum_nights": "365", "availability_365": "351"}, {"": "25658", "id": "762028284985982407", "name": "Rental unit in Los Angeles \u00b7 \u26054.82 \u00b7 2 bedrooms \u00b7 2 beds \u00b7 2 baths", "host_id": "230016718", "price": "$363.00", "minimum_nights": "2", "maximum_nights": "30", "availability_365": "42"}, {"": "25659", "id": "645778518636423919", "name": "Home in Los Angeles \u00b7 \u26054.80 \u00b7 3 bedrooms \u00b7 5 beds \u00b7 2 baths", "host_id": "8185146", "price": "$257.00", "minimum_nights": "1", "maximum_nights": "1125", "availability_365": "335"}, {"": "25660", "id": "795805542205823870", "name": "Home in Inglewood \u00b7 2 bedrooms \u00b7 3 beds \u00b7 1 bath", "host_id": "448843163", "price": "$84.00", "minimum_nights": "31", "maximum_nights": "365", "availability_365": "31"}, {"": "25661", "id": "862231141087546423", "name": "Rental unit in Los Angeles \u00b7 \u26054.64 \u00b7 2 bedrooms \u00b7 3 beds \u00b7 2 baths", "host_id": "230016718", "price": "$274.00", "minimum_nights": "1", "maximum_nights": "1125", "availability_365": "34"}, {"": "25662", "id": "53125", "name": "Boutique hotel in Santa Monica \u00b7 \u26054.23 \u00b7 Studio \u00b7 1 private bath", "host_id": "239712", "price": "$187.00", "minimum_nights": "2", "maximum_nights": "365", "availability_365": "259"}, {"": "25663", "id": "49816377", "name": "Condo in Los Angeles \u00b7 Studio \u00b7 1 bed \u00b7 1 bath", "host_id": "401774997", "price": "$130.00", "minimum_nights": "30", "maximum_nights": "90", "availability_365": "242"}, {"": "25664", "id": "53518350", "name": "Rental unit in Santa Monica \u00b7 \u26054.65 \u00b7 1 bedroom \u00b7 1 bed \u00b7 1 bath", "host_id": "433112347", "price": "$233.00", "minimum_nights": "30", "maximum_nights": "1125", "availability_365": "365"}, {"": "25665", "id": "795699984323547500", "name": "Home in Los Angeles \u00b7 4 bedrooms \u00b7 5 beds \u00b7 4.5 baths", "host_id": "9720386", "price": "$799.00", "minimum_nights": "30", "maximum_nights": "365", "availability_365": "30"}, {"": "25666", "id": "46860959", "name": "Rental unit in Los Angeles \u00b7 \u26055.0 \u00b7 2 bedrooms \u00b7 2 beds \u00b7 2 baths", "host_id": "374464274", "price": "$125.00", "minimum_nights": "31", "maximum_nights": "365", "availability_365": "261"}, {"": "25667", "id": "797777120240074311", "name": "Home in Rosemead \u00b7 \u26053.75 \u00b7 1 bedroom \u00b7 1 bed \u00b7 1 shared bath", "host_id": "261384930", "price": "$42.00", "minimum_nights": "3", "maximum_nights": "365", "availability_365": "0"}, {"": "25668", "id": "12384924", "name": "Rental unit in Venice \u00b7 \u26055.0 \u00b7 2 bedrooms \u00b7 2 beds \u00b7 1 bath", "host_id": "62396579", "price": "$150.00", "minimum_nights": "60", "maximum_nights": "365", "availability_365": "363"}, {"": "25669", "id": "863055112873207861", "name": "Rental unit in Santa Monica \u00b7 \u26054.88 \u00b7 2 bedrooms \u00b7 2 beds \u00b7 2 baths", "host_id": "138092283", "price": "$335.00", "minimum_nights": "2", "maximum_nights": "365", "availability_365": "355"}, {"": "25670", "id": "625638745207436659", "name": "Serviced apartment in Los Angeles \u00b7 \u26054.94 \u00b7 2 bedrooms \u00b7 2 beds \u00b7 2 baths", "host_id": "430094148", "price": "$292.00", "minimum_nights": "5", "maximum_nights": "365", "availability_365": "75"}, {"": "25671", "id": "5447959", "name": "Rental unit in Los Angeles \u00b7 \u26054.80 \u00b7 1 bedroom \u00b7 1 bed \u00b7 1 bath", "host_id": "2180237", "price": "$285.00", "minimum_nights": "4", "maximum_nights": "1125", "availability_365": "337"}, {"": "25672", "id": "35840229", "name": "Guest suite in Los Angeles \u00b7 \u26055.0 \u00b7 Studio \u00b7 1 bed \u00b7 1 bath", "host_id": "269591141", "price": "$100.00", "minimum_nights": "30", "maximum_nights": "90", "availability_365": "35"}, {"": "25673", "id": "48815316", "name": "Rental unit in Los Angeles \u00b7 \u26054.25 \u00b7 Studio \u00b7 2 beds \u00b7 1 bath", "host_id": "374464274", "price": "$80.00", "minimum_nights": "31", "maximum_nights": "365", "availability_365": "360"}, {"": "25674", "id": "24301091", "name": "Home in Los Angeles \u00b7 \u26054.20 \u00b7 3 bedrooms \u00b7 3 beds \u00b7 1 bath", "host_id": "6172811", "price": "$219.00", "minimum_nights": "30", "maximum_nights": "90", "availability_365": "32"}, {"": "25675", "id": "43667933", "name": "Home in Burbank \u00b7 \u26054.79 \u00b7 4 bedrooms \u00b7 5 beds \u00b7 2 baths", "host_id": "348745371", "price": "$429.00", "minimum_nights": "30", "maximum_nights": "1125", "availability_365": "222"}, {"": "25676", "id": "882226665175044918", "name": "Home in Torrance \u00b7 \u26054.40 \u00b7 4 bedrooms \u00b7 5 beds \u00b7 3 baths", "host_id": "220073363", "price": "$303.00", "minimum_nights": "4", "maximum_nights": "365", "availability_365": "343"}, {"": "25677", "id": "46282385", "name": "Condo in Los Angeles \u00b7 2 bedrooms \u00b7 3 beds \u00b7 2 baths", "host_id": "230016718", "price": "$500.00", "minimum_nights": "31", "maximum_nights": "1125", "availability_365": "31"}, {"": "25678", "id": "613133075358665543", "name": "Condo in Marina del Rey \u00b7 2 bedrooms \u00b7 4 beds \u00b7 2.5 baths", "host_id": "133838847", "price": "$170.00", "minimum_nights": "30", "maximum_nights": "60", "availability_365": "268"}, {"": "25679", "id": "565836", "name": "Home in Venice \u00b7 \u26054.95 \u00b7 2 bedrooms \u00b7 2 beds \u00b7 2 baths", "host_id": "2782528", "price": "$355.00", "minimum_nights": "31", "maximum_nights": "365", "availability_365": "364"}, {"": "25680", "id": "6629501", "name": "Home in Venice \u00b7 \u26054.93 \u00b7 1 bedroom \u00b7 2 beds \u00b7 1 bath", "host_id": "34703692", "price": "$500.00", "minimum_nights": "30", "maximum_nights": "120", "availability_365": "363"}, {"": "25681", "id": "45988868", "name": "Rental unit in Santa Monica \u00b7 Studio \u00b7 1 bath", "host_id": "35923845", "price": "$90.00", "minimum_nights": "30", "maximum_nights": "90", "availability_365": "90"}, {"": "25682", "id": "774091521910050547", "name": "Home in Los Angeles \u00b7 4 bedrooms \u00b7 4 beds \u00b7 4.5 baths", "host_id": "177665115", "price": "$2,850.00", "minimum_nights": "30", "maximum_nights": "365", "availability_365": "364"}, {"": "25683", "id": "47844580", "name": "Rental unit in Los Angeles \u00b7 Studio \u00b7 1 bed \u00b7 1 bath", "host_id": "134267499", "price": "$87.00", "minimum_nights": "31", "maximum_nights": "90", "availability_365": "83"}, {"": "25684", "id": "781261959192941736", "name": "Home in Los Angeles \u00b7 \u26055.0 \u00b7 2 bedrooms \u00b7 3 beds \u00b7 1 bath", "host_id": "41113264", "price": "$300.00", "minimum_nights": "2", "maximum_nights": "365", "availability_365": "135"}, {"": "25685", "id": "36208004", "name": "Home in Los Angeles \u00b7 \u26054.93 \u00b7 1 bedroom \u00b7 1 bed \u00b7 1 bath", "host_id": "6742105", "price": "$196.00", "minimum_nights": "1", "maximum_nights": "1125", "availability_365": "81"}, {"": "25686", "id": "53659302", "name": "Rental unit in Santa Monica \u00b7 \u26054.75 \u00b7 1 bedroom \u00b7 1 bed \u00b7 1 bath", "host_id": "137877395", "price": "$135.00", "minimum_nights": "31", "maximum_nights": "1125", "availability_365": "216"}, {"": "25687", "id": "849437940262471093", "name": "Rental unit in Santa Monica \u00b7 \u26054.88 \u00b7 2 bedrooms \u00b7 2 beds \u00b7 2 baths", "host_id": "138092283", "price": "$451.00", "minimum_nights": "2", "maximum_nights": "365", "availability_365": "171"}, {"": "25688", "id": "690646891241821914", "name": "Home in Los Angeles \u00b7 \u26054.53 \u00b7 4 bedrooms \u00b7 4 beds \u00b7 0 baths", "host_id": "474381973", "price": "$900.00", "minimum_nights": "2", "maximum_nights": "21", "availability_365": "171"}, {"": "25689", "id": "731101067563395706", "name": "Condo in West Hollywood \u00b7 1 bedroom \u00b7 2 beds \u00b7 1.5 baths", "host_id": "482358106", "price": "$100.00", "minimum_nights": "30", "maximum_nights": "45", "availability_365": "150"}, {"": "25690", "id": "895727692325948625", "name": "Rental unit in Santa Monica \u00b7 2 bedrooms \u00b7 2 beds \u00b7 2 baths", "host_id": "139896539", "price": "$315.00", "minimum_nights": "30", "maximum_nights": "365", "availability_365": "280"}, {"": "25691", "id": "944586524363948349", "name": "Home in Bell Gardens \u00b7 \u26054.78 \u00b7 1 bedroom \u00b7 1 bed \u00b7 1 bath", "host_id": "50006816", "price": "$120.00", "minimum_nights": "1", "maximum_nights": "90", "availability_365": "81"}, {"": "25692", "id": "48724516", "name": "Condo in Marina del Rey \u00b7 2 bedrooms \u00b7 2 beds \u00b7 2.5 baths", "host_id": "9897054", "price": "$350.00", "minimum_nights": "30", "maximum_nights": "90", "availability_365": "0"}, {"": "25693", "id": "52372538", "name": "Serviced apartment in Lancaster \u00b7 \u26055.0 \u00b7 1 bedroom \u00b7 1 bed \u00b7 1 bath", "host_id": "267485780", "price": "$105.00", "minimum_nights": "3", "maximum_nights": "30", "availability_365": "365"}, {"": "25694", "id": "46110244", "name": "Condo in Los Angeles \u00b7 1 bedroom \u00b7 1 shared bath", "host_id": "288005077", "price": "$26.00", "minimum_nights": "32", "maximum_nights": "1125", "availability_365": "284"}, {"": "25695", "id": "38408015", "name": "Home in Los Angeles \u00b7 \u26055.0 \u00b7 2 bedrooms \u00b7 2 beds \u00b7 2 baths", "host_id": "6742105", "price": "$581.00", "minimum_nights": "30", "maximum_nights": "1125", "availability_365": "141"}, {"": "25696", "id": "1712418", "name": "Home in Venice \u00b7 \u26054.88 \u00b7 2 bedrooms \u00b7 2 beds \u00b7 2.5 baths", "host_id": "6825086", "price": "$725.00", "minimum_nights": "30", "maximum_nights": "30", "availability_365": "246"}, {"": "25697", "id": "31475343", "name": "Condo in Los Angeles \u00b7 1 bedroom \u00b7 1 bed \u00b7 1 bath", "host_id": "164998304", "price": "$164.00", "minimum_nights": "30", "maximum_nights": "365", "availability_365": "365"}, {"": "25698", "id": "792032291889191931", "name": "Rental unit in Santa Monica \u00b7 \u26054.78 \u00b7 2 bedrooms \u00b7 2 beds \u00b7 2 baths", "host_id": "35795034", "price": "$330.00", "minimum_nights": "2", "maximum_nights": "365", "availability_365": "327"}, {"": "25699", "id": "51282870", "name": "Bungalow in Los Angeles \u00b7 \u26055.0 \u00b7 2 bedrooms \u00b7 1 bed \u00b7 2 baths", "host_id": "30988645", "price": "$800.00", "minimum_nights": "3", "maximum_nights": "1125", "availability_365": "62"}]